aiosu/__init__.py
aiosu/events.py
aiosu/exceptions.py
aiosu/helpers.py
aiosu/models/__init__.py
aiosu/models/artist.py
aiosu/models/backgrounds.py
aiosu/models/base.py
aiosu/models/beatmap.py
aiosu/models/changelog.py
aiosu/models/chat.py
aiosu/models/comment.py
aiosu/models/common.py
aiosu/models/event.py
aiosu/models/files/__init__.py
aiosu/models/files/replay.py
aiosu/models/forum.py
aiosu/models/gamemode.py
aiosu/models/kudosu.py
aiosu/models/lazer.py
aiosu/models/legacy/__init__.py
aiosu/models/legacy/match.py
aiosu/models/legacy/replay.py
aiosu/models/mods.py
aiosu/models/multiplayer.py
aiosu/models/news.py
aiosu/models/oauthtoken.py
aiosu/models/performance.py
aiosu/models/rankings.py
aiosu/models/scopes.py
aiosu/models/score.py
aiosu/models/search.py
aiosu/models/spotlight.py
aiosu/models/user.py
aiosu/models/wiki.py
aiosu/py.typed
aiosu/utils/__init__.py
aiosu/utils/accuracy.py
aiosu/utils/auth.py
aiosu/utils/binary.py
aiosu/utils/performance.py
aiosu/utils/replay.py
aiosu/v1/__init__.py
aiosu/v1/client.py
aiosu/v2/__init__.py
aiosu/v2/client.py
aiosu/v2/clientstorage.py
aiosu/v2/repository/__init__.py
aiosu/v2/repository/oauthtoken.py
aiosu-2.3.5.dist-info/METADATA
aiosu-2.3.5.dist-info/WHEEL
aiosu-2.3.5.dist-info/licenses/LICENSE
aiosu-2.3.5.dist-info/RECORD
