Metadata-Version: 2.4
Name: aiosu
Version: 2.3.5
Summary: Simple and fast osu! API v1 and v2 library
License-Expression: GPL-3.0-or-later
License-File: LICENSE
Keywords: osu!,osu,api
Author: Nice Aesthetics
Author-email: nice@aesth.dev
Requires-Python: >=3.10,<4.0
Classifier: Programming Language :: Python :: 3
Classifier: Programming Language :: Python :: 3.10
Classifier: Programming Language :: Python :: 3.11
Classifier: Programming Language :: Python :: 3.12
Classifier: Programming Language :: Python :: 3.13
Classifier: Programming Language :: Python :: 3.14
Provides-Extra: docs
Provides-Extra: test
Requires-Dist: Sphinx ; extra == "docs"
Requires-Dist: aiohttp (>=3.8.3)
Requires-Dist: aiolimiter (>=1.0.0)
Requires-Dist: emojiflags (>=0.1.1)
Requires-Dist: furo ; extra == "docs"
Requires-Dist: orjson (>=3.8.3)
Requires-Dist: pydantic (>=2.0.3)
Requires-Dist: pyjwt (>=2.6.0)
Requires-Dist: pytest ; extra == "test"
Requires-Dist: pytest-asyncio ; extra == "test"
Requires-Dist: pytest-mock ; extra == "test"
Requires-Dist: toml ; extra == "docs"
Requires-Dist: toml ; extra == "test"
Requires-Dist: types-toml ; extra == "test"
Project-URL: Documentation, https://aiosu.readthedocs.io/
Project-URL: Repository, https://github.com/NiceAesth/aiosu
